coast_core/__init__.py
coast_core/_version.py
coast_core/citations.py
coast_core/clarity_of_writing.py
coast_core/code_detection.py
coast_core/events.py
coast_core/markers.py
coast_core/named_entities.py
coast_core/ngram_extraction.py
coast_core/utils.py
coast_core/resources/__init__.py
coast_core/resources/data/citations_classification.json
coast_core/resources/data/keywords.txt
coast_core/resources/data/patterns.json
coast_core/resources/example/config_file.json
coast_core/resources/example/markers_experience_9.json
coast_core/resources/example/markers_reasoning_10.json
coast_core/resources/example/markers_reasoning_86.json
coast_core/resources/stanford/english.conll.4class.distsim.crf.ser.gz
coast_core/resources/stanford/stanford-ner.jar
coast_core-1.0.1.dist-info/METADATA
coast_core-1.0.1.dist-info/RECORD
coast_core-1.0.1.dist-info/WHEEL
coast_core-1.0.1.dist-info/top_level.txt
