Metadata-Version: 2.1
Name: coast-core
Version: 1.0.1
Summary: Core functionality of COAST
Home-page: https://github.com/zedrem/coast_core
Author: Ashley Williams
Author-email: ashley.williams@pg.canterbury.ac.nz
License: MIT license
Keywords: coast_core
Platform: UNKNOWN
Classifier: Development Status :: 5 - Production/Stable
Classifier: Intended Audience :: Developers
Classifier: Intended Audience :: Education
Classifier: Intended Audience :: Science/Research
Classifier: License :: OSI Approved :: MIT License
Classifier: Natural Language :: English
Classifier: Programming Language :: Python :: 3.5
Classifier: Programming Language :: Python :: 3.6
Requires-Dist: six
Requires-Dist: bs4
Requires-Dist: html5lib
Requires-Dist: textstat
Requires-Dist: nltk
Requires-Dist: language-check
Requires-Dist: textblob
Requires-Dist: langdetect
